{
  "updated": "2026-03-05T18:21:33.624177-05:00Z",
  "metro": {
    "station": "Rosemont",
    "next_departures": [
      "18:26",
      "18:29",
      "18:30",
      "18:35",
      "18:39",
      "18:40",
      "18:45",
      "18:49",
      "18:50",
      "18:55",
      "18:59",
      "19:00",
      "19:05",
      "19:09",
      "19:10",
      "19:16",
      "19:19",
      "19:22",
      "19:28",
      "19:29",
      "19:34",
      "19:39",
      "19:40",
      "19:46",
      "19:49",
      "19:52",
      "19:58",
      "19:59",
      "20:04",
      "20:09"
    ],
    "next_departure": "18:26",
    "minutes_until": 5,
    "line_color": "#D95700"
  },
  "assets": [
    {
      "symbol": "XEQT",
      "price": 40.94,
      "change_percent": -1.06,
      "color": "blue"
    },
    {
      "symbol": "BTC",
      "price": 71179.42,
      "change_percent": -2.13,
      "color": "orange"
    },
    {
      "symbol": "GOLD",
      "price": 5093.2,
      "change_percent": 0.29,
      "color": "yellow"
    },
    {
      "symbol": "SPX",
      "price": 6830.71,
      "change_percent": -0.56,
      "color": "purple"
    }
  ],
  "market_open": false,
  "stock": {
    "symbol": "XEQT",
    "price": 40.94,
    "change_percent": -1.06,
    "market_open": false
  },
  "time": {
    "display": "18:21",
    "timezone": "America/Montreal",
    "date": "MAR 05"
  }
}