{
  "updated": "2026-02-13T09:04:13.118251-05:00Z",
  "metro": {
    "station": "Rosemont",
    "next_departures": [
      "09:05",
      "09:07",
      "09:10",
      "09:12",
      "09:13",
      "09:14",
      "09:17",
      "09:20",
      "09:21",
      "09:22",
      "09:24",
      "09:28",
      "09:29",
      "09:30",
      "09:32",
      "09:35",
      "09:37",
      "09:39",
      "09:43",
      "09:45",
      "09:47",
      "09:48",
      "09:53",
      "09:56",
      "09:58",
      "10:01",
      "10:03",
      "10:05",
      "10:08",
      "10:09"
    ],
    "next_departure": "09:05",
    "minutes_until": 1,
    "line_color": "#D95700"
  },
  "stock": {
    "symbol": "XEQT",
    "price": 41.02,
    "change_percent": -1.35,
    "market_open": false
  },
  "time": {
    "display": "09:04",
    "timezone": "America/Montreal",
    "date": "FEB 13"
  }
}