{
  "updated": "2026-02-09T21:02:08.349463-05:00Z",
  "metro": {
    "station": "Rosemont",
    "next_departures": [
      "21:04",
      "21:10",
      "21:16",
      "21:22",
      "21:28",
      "21:34",
      "21:40",
      "21:46",
      "21:52",
      "21:58",
      "22:04",
      "22:10",
      "22:16",
      "22:22",
      "22:28",
      "22:33",
      "22:39",
      "22:46",
      "22:53",
      "23:00",
      "23:07",
      "23:14",
      "23:21",
      "23:28",
      "23:36",
      "23:44",
      "23:52",
      "00:00",
      "00:08",
      "00:16"
    ],
    "next_departure": "21:04",
    "minutes_until": 2,
    "line_color": "#D95700"
  },
  "stock": {
    "symbol": "XEQT",
    "price": 41.4,
    "change_percent": 0.58,
    "market_open": false
  },
  "time": {
    "display": "21:02",
    "timezone": "America/Montreal",
    "date": "FEB 09"
  }
}