{
  "updated": "2026-03-06T14:06:14.993597-05:00Z",
  "metro": {
    "station": "Rosemont",
    "next_departures": [
      "14:07",
      "14:08",
      "14:13",
      "14:15",
      "14:19",
      "14:20",
      "14:21",
      "14:25",
      "14:27",
      "14:28",
      "14:31",
      "14:33",
      "14:35",
      "14:37",
      "14:40",
      "14:42",
      "14:43",
      "14:46",
      "14:49",
      "14:53",
      "14:55",
      "14:56",
      "15:00",
      "15:01",
      "15:02",
      "15:06",
      "15:07",
      "15:09",
      "15:12",
      "15:13"
    ],
    "next_departure": "14:07",
    "minutes_until": 1,
    "line_color": "#D95700"
  },
  "assets": [
    {
      "symbol": "XEQT",
      "price": 40.35,
      "change_percent": -1.44,
      "color": "blue"
    },
    {
      "symbol": "BTC",
      "price": 68282.82,
      "change_percent": -3.66,
      "color": "orange"
    },
    {
      "symbol": "GOLD",
      "price": 5169.4,
      "change_percent": 1.79,
      "color": "yellow"
    },
    {
      "symbol": "SPX",
      "price": 6754.95,
      "change_percent": -1.11,
      "color": "purple"
    }
  ],
  "market_open": true,
  "stock": {
    "symbol": "XEQT",
    "price": 40.35,
    "change_percent": -1.44,
    "market_open": true
  },
  "time": {
    "display": "14:06",
    "timezone": "America/Montreal",
    "date": "MAR 06"
  }
}